neon_solvers/__init__.py
neon_solvers/solver.py
neon_solvers-0.0.2a1.dist-info/LICENSE.md
neon_solvers-0.0.2a1.dist-info/METADATA
neon_solvers-0.0.2a1.dist-info/WHEEL
neon_solvers-0.0.2a1.dist-info/top_level.txt
neon_solvers-0.0.2a1.dist-info/RECORD
