Metadata-Version: 2.1
Name: neon-solvers
Version: 0.0.2a1
Summary: neon question solver plugin framework
Home-page: https://github.com/NeonGeckoCom/neon_solvers
Author: Neongecko
Author-email: developers@neon.ai
License: bsd3
Platform: UNKNOWN
Requires-Dist: quebra-frases
Requires-Dist: json-database
Requires-Dist: ovos-plugin-manager
Requires-Dist: neon-lang-plugin-libretranslate
